pop_loop/conf.py
pop_loop/version.py
pop_loop/loop/auto.py
pop_loop/loop/curio_loop.py
pop_loop/loop/init.py
pop_loop/loop/proactor.py
pop_loop/loop/qt.py
pop_loop/loop/selector_unix.py
pop_loop/loop/selector_win.py
pop_loop/loop/tornado_loop.py
pop_loop/loop/trio_loop.py
pop_loop/loop/twisted_loop.py
pop_loop/loop/uv_loop.py
pop_loop/loop/contracts/init.py
pop_loop-1.1.0.dist-info/LICENSE
pop_loop-1.1.0.dist-info/METADATA
pop_loop-1.1.0.dist-info/WHEEL
pop_loop-1.1.0.dist-info/top_level.txt
pop_loop-1.1.0.dist-info/RECORD
