Metadata-Version: 2.1
Name: pop-loop
Version: 1.1.0
Summary: Plugins that allow alternate io loops to be used to run asynchronous code in pop projects
Home-page: https://vmware.gitlab.io/pop/pop-loop/en/latest/index.html
Author: VMware, Inc.
Author-email: idemproject@vmware.com
License: Apache Software License 2.0
Project-URL: Code, https://gitlab.com/vmware/pop/pop-loop
Project-URL: Issue tracker, https://gitlab.com/vmware/pop/pop-loop/issues
Platform: UNKNOWN
Classifier: Environment :: Console
Classifier: Intended Audience :: Developers
Classifier: Intended Audience :: Information Technology
Classifier: Intended Audience :: System Administrators
Classifier: Operating System :: OS Independent
Classifier: Programming Language :: Python
Classifier: Programming Language :: Python :: 3.8
Classifier: Programming Language :: Python :: 3.9
Classifier: Programming Language :: Python :: 3.10
Classifier: Programming Language :: Python :: 3.11
Classifier: Development Status :: 5 - Production/Stable
Classifier: License :: OSI Approved :: Apache Software License
Requires-Python: >=3.8
Provides-Extra: full
Provides-Extra: trio
Provides-Extra: qt
Provides-Extra: curio
Provides-Extra: uvloop
Provides-Extra: twisted
Provides-Extra: tornado
License-File: LICENSE
